clearcli/__init__.py
clearcli/commands.py
clearcli/mock.py
clearcli-1.0.1.dist-info/LICENSE
clearcli-1.0.1.dist-info/WHEEL
clearcli-1.0.1.dist-info/METADATA
clearcli-1.0.1.dist-info/RECORD
