Metadata-Version: 2.1
Name: clearcli
Version: 1.0.1
Summary: Build Command Line Interface with ease
Home-page: https://github.com/thmahe/clearcli
License: GPL-3.0-only
Keywords: argparse,cli
Author: Thomas Mahé
Author-email: contact@tmahe.dev
Requires-Python: >=3.7,<4.0
Classifier: Development Status :: 5 - Production/Stable
Classifier: Environment :: Console
Classifier: License :: OSI Approved :: GNU General Public License v3 (GPLv3)
Classifier: Programming Language :: Python :: 3
Classifier: Programming Language :: Python :: 3.10
Classifier: Programming Language :: Python :: 3.7
Classifier: Programming Language :: Python :: 3.8
Classifier: Programming Language :: Python :: 3.9
Classifier: Topic :: Software Development :: Libraries :: Python Modules
Classifier: Topic :: Software Development :: Testing :: Mocking
Provides-Extra: test
Project-URL: Documentation, https://clearcli.readthedocs.io/en/latest/
Project-URL: Repository, https://github.com/thmahe/clearcli
